{
    "last_update": "2026-03-03",
    "data": [
        {
            "symbol": "NVDA",
            "name": "Nvidia (AI之王)",
            "category": "美國科技",
            "price": 182.48,
            "rsi": 41.9,
            "lights": {
                "short": "⚪",
                "mid": "⚪",
                "long": "⚪"
            },
            "status": "平穩行駛中",
            "vol_ratio": 0.79,
            "chip_signal": "💤 散戶盤整"
        },
        {
            "symbol": "TSLA",
            "name": "Tesla (電動車)",
            "category": "美國科技",
            "price": 403.32,
            "rsi": 40.8,
            "lights": {
                "short": "⚪",
                "mid": "⚪",
                "long": "⚪"
            },
            "status": "平穩行駛中",
            "vol_ratio": 0.95,
            "chip_signal": "💤 散戶盤整"
        },
        {
            "symbol": "SPY",
            "name": "S&P 500 ETF",
            "category": "美股大盤",
            "price": 686.38,
            "rsi": 42.4,
            "lights": {
                "short": "⚪",
                "mid": "⚪",
                "long": "⚪"
            },
            "status": "平穩行駛中",
            "vol_ratio": 1.14,
            "chip_signal": "💤 散戶盤整"
        },
        {
            "symbol": "0050.TW",
            "name": "元大台灣50",
            "category": "台股龍頭",
            "price": 79.85,
            "rsi": 75.6,
            "lights": {
                "short": "⚪",
                "mid": "🟡",
                "long": "🟢"
            },
            "status": "現在超火熱",
            "vol_ratio": 0.42,
            "chip_signal": "💤 散戶盤整"
        },
        {
            "symbol": "2330.TW",
            "name": "台積電",
            "category": "台股龍頭",
            "price": 1970.0,
            "rsi": 74.1,
            "lights": {
                "short": "⚪",
                "mid": "🟡",
                "long": "🟢"
            },
            "status": "現在超火熱",
            "vol_ratio": 0.26,
            "chip_signal": "💤 散戶盤整"
        },
        {
            "symbol": "2303.TW",
            "name": "聯電",
            "category": "晶圓代工",
            "price": 64.0,
            "rsi": 56.3,
            "lights": {
                "short": "⚪",
                "mid": "⚪",
                "long": "🟢"
            },
            "status": "平穩行駛中",
            "vol_ratio": 0.22,
            "chip_signal": "💤 散戶盤整"
        },
        {
            "symbol": "9802.TW",
            "name": "鈺齊-KY",
            "category": "運動鞋",
            "price": 94.4,
            "rsi": 49.3,
            "lights": {
                "short": "⚪",
                "mid": "⚪",
                "long": "⚪"
            },
            "status": "平穩行駛中",
            "vol_ratio": 0.19,
            "chip_signal": "💤 散戶盤整"
        },
        {
            "symbol": "9910.TW",
            "name": "豐泰",
            "category": "運動鞋",
            "price": 92.4,
            "rsi": 36.2,
            "lights": {
                "short": "⚪",
                "mid": "⚪",
                "long": "⚪"
            },
            "status": "平穩行駛中",
            "vol_ratio": 0.04,
            "chip_signal": "💤 散戶盤整"
        },
        {
            "symbol": "9904.TW",
            "name": "寶成",
            "category": "運動鞋",
            "price": 30.6,
            "rsi": 52.7,
            "lights": {
                "short": "⚪",
                "mid": "⚪",
                "long": "⚪"
            },
            "status": "平穩行駛中",
            "vol_ratio": 0.33,
            "chip_signal": "💤 散戶盤整"
        }
    ]
}